extralog/__init__.py
extralog/extralog.py
extralog/scope.py
extralog-0.1.1.dist-info/METADATA
extralog-0.1.1.dist-info/WHEEL
extralog-0.1.1.dist-info/RECORD
