Metadata-Version: 2.1
Name: extralog
Version: 0.1.1
Summary: 
Author: 'Gilad Barnea'
Author-email: giladbrn@gmail.com
Requires-Python: >=3.9,<4.0
Classifier: Programming Language :: Python :: 3
Classifier: Programming Language :: Python :: 3.9
Classifier: Programming Language :: Python :: 3.10
Classifier: Programming Language :: Python :: 3.11
Requires-Dist: typing-extensions (>=4.8.0,<5.0.0)
